Metadata-Version: 1.1
Name: ExtractandPlot
Version: 0.0.4
Summary: Download file from google drive and Plot it using scatter plot
Home-page: UNKNOWN
Author: Hardik Choudhary
Author-email: hardikchoudhary2698@gmail.com
License: MIT
Platform: UNKNOWN
Classifier: Development Status :: 5 - Production/Stable
Classifier: Intended Audience :: Education
Classifier: Operating System :: Microsoft :: Windows :: Windows 10
Classifier: License :: OSI Approved :: MIT License
Classifier: Programming Language :: Python :: 3
